

[
  { "symbol": "النون" },
  { "symbol": "أَنْ" },
  { "symbol": "أَنْعَمْتَ" },
  { "symbol": "إِنْ" },
  { "symbol": "مِنْهَا" },
  { "symbol": "أُنْ" },
  { "symbol": "أُنْثَى" },
  { "symbol": "نَ" },
  { "symbol": "نَحْنُ" },
  { "symbol": "نِ" },
  { "symbol": "نِعْمَتِي" },
  { "symbol": "نُ" },
  { "symbol": "نُسَبِّحَ" },
  { "symbol": "نَا" },
  { "symbol": "نَارًا" },
  { "symbol": "نِي" },
  { "symbol": "حَنِيفًا" },
  { "symbol": "نُو" },
  { "symbol": "نُوحِي" }
]

